unicef_restlib/__init__.py
unicef_restlib/fields.py
unicef_restlib/metadata.py
unicef_restlib/pagination.py
unicef_restlib/permissions.py
unicef_restlib/routers.py
unicef_restlib/serializers.py
unicef_restlib/utils.py
unicef_restlib/views.py
unicef_restlib/__pycache__/__init__.cpython-39.pyc
unicef_restlib/__pycache__/fields.cpython-39.pyc
unicef_restlib/__pycache__/metadata.cpython-39.pyc
unicef_restlib/__pycache__/pagination.cpython-39.pyc
unicef_restlib/__pycache__/permissions.cpython-39.pyc
unicef_restlib/__pycache__/routers.cpython-39.pyc
unicef_restlib/__pycache__/serializers.cpython-39.pyc
unicef_restlib/__pycache__/utils.cpython-39.pyc
unicef_restlib/__pycache__/views.cpython-39.pyc
unicef_restlib-0.7.dist-info/LICENSE
unicef_restlib-0.7.dist-info/METADATA
unicef_restlib-0.7.dist-info/WHEEL
unicef_restlib-0.7.dist-info/top_level.txt
unicef_restlib-0.7.dist-info/RECORD
