Metadata-Version: 2.1
Name: unicef-restlib
Version: 0.7
Summary: Django package that handles exporting of data
Home-page: https://github.com/unicef/unicef-rest-export
Author: UNICEF
Author-email: dev@unicef.org
License: Apache 2 License
Platform: any
Classifier: Environment :: Web Environment
Classifier: Programming Language :: Python :: 3.7
Classifier: Programming Language :: Python :: 3.8
Classifier: Programming Language :: Python :: 3.9
Classifier: Framework :: Django
Classifier: Framework :: Django :: 2.2
Classifier: Framework :: Django :: 3.0
Classifier: Framework :: Django :: 3.1
Classifier: Framework :: Django :: 3.2
Classifier: Intended Audience :: Developers
Requires-Dist: django
Requires-Dist: django-fsm
Requires-Dist: djangorestframework
Requires-Dist: djangorestframework-recursive
Requires-Dist: drf-nested-routers
Requires-Dist: unicef-djangolib
Provides-Extra: test
Requires-Dist: coverage ; extra == 'test'
Requires-Dist: django-fsm ; extra == 'test'
Requires-Dist: factory-boy ; extra == 'test'
Requires-Dist: faker ; extra == 'test'
Requires-Dist: flake8 ; extra == 'test'
Requires-Dist: isort ; extra == 'test'
Requires-Dist: pyflakes ; extra == 'test'
Requires-Dist: pytest ; extra == 'test'
Requires-Dist: pytest-cov ; extra == 'test'
Requires-Dist: pytest-django ; extra == 'test'
Requires-Dist: pytest-echo ; extra == 'test'
Requires-Dist: pytest-pythonpath ; extra == 'test'
